rofi_pulse/__init__.py
rofi_pulse/rofi_pulse.py
rofi_pulse-1.0.0.dist-info/METADATA
rofi_pulse-1.0.0.dist-info/WHEEL
rofi_pulse-1.0.0.dist-info/entry_points.txt
rofi_pulse-1.0.0.dist-info/top_level.txt
rofi_pulse-1.0.0.dist-info/RECORD
