Metadata-Version: 2.1
Name: rofi-pulse
Version: 1.0.0
Summary: Control pulseaudio with rofi
Home-page: https://github.com/id405/rofi-pulse
Author: Id405
Author-email: UNKNOWN
License: GPL V3.0
Platform: UNKNOWN
Requires-Dist: pulsectl
Requires-Dist: python-rofi
